CHANGES.rst
MANIFEST.in
MetlogPy.spec
README.rst
setup.py
docs/Makefile
docs/conf.py
docs/config.rst
docs/getstarted.rst
docs/index.rst
docs/api/client.rst
docs/api/config.rst
docs/api/decorators.rst
docs/api/exceptions.rst
docs/api/filters.rst
docs/api/senders.rst
metlog/__init__.py
metlog/client.py
metlog/command.py
metlog/config.py
metlog/exceptions.py
metlog/filters.py
metlog/holder.py
metlog/logging.py
metlog/path.py
metlog/decorators/__init__.py
metlog/decorators/base.py
metlog/decorators/stats.py
metlog/decorators/util.py
metlog/senders/__init__.py
metlog/senders/dev.py
metlog/senders/logging.py
metlog/senders/udp.py
metlog/senders/zmq.py
metlog/tests/__init__.py
metlog/tests/plugin.py
metlog/tests/plugin_exception.py
metlog/tests/sync_publisher.py
metlog/tests/sync_subscriber.py
metlog/tests/test_client.py
metlog/tests/test_config.py
metlog/tests/test_decorators.py
metlog/tests/test_filters.py
metlog/tests/test_logging.py
metlog/tests/test_senders.py
metlog/tests/test_timer.py
metlog_py.egg-info/PKG-INFO
metlog_py.egg-info/SOURCES.txt
metlog_py.egg-info/dependency_links.txt
metlog_py.egg-info/entry_points.txt
metlog_py.egg-info/not-zip-safe
metlog_py.egg-info/requires.txt
metlog_py.egg-info/top_level.txt