Metadata-Version: 1.0
Name: metlog-py
Version: 0.10.0
Summary: Metrics Logging
Home-page: https://github.com/mozilla-services/metlog-py
Author: Rob Miller
Author-email: rmiller@mozilla.com
License: MPLv2.0
Keywords: metlog metrics logging client
Platform: UNKNOWN
Classifier: License :: OSI Approved :: Mozilla Public License 2.0 (MPL 2.0)
